atd/__init__.py
atd/atd.py
atd/atq.py
atd/config.py
atd/tests.py
python_atd-0.2.1.dist-info/LICENSE
python_atd-0.2.1.dist-info/METADATA
python_atd-0.2.1.dist-info/WHEEL
python_atd-0.2.1.dist-info/top_level.txt
python_atd-0.2.1.dist-info/RECORD
