Metadata-Version: 2.1
Name: python-atd
Version: 0.2.1
Summary: Unix `at` scheduler, for Python 3 and Python 2. Supports atq, atd, & atrm
Home-page: http://github.com/ctrlcctrlv/python-atd
Author: Fredrick Brennan
Author-email: copypaste@kittens.ph
License: MIT
Keywords: atq atrm atd at
Platform: UNKNOWN
Classifier: Programming Language :: Python :: 3
Classifier: Programming Language :: Python :: 2
Classifier: License :: OSI Approved :: MIT License
Classifier: Operating System :: OS Independent
